[
  {
    "model": "organization.organization",
    "pk": 1,
    "fields": {
      "title": "org1",
      "short_name": "org1",
      "organization_kind": null,
      "methodology": "bla",
      "source_detail_methodology": "blaa",
      "parent": null
    }
  },
  {
    "model": "organization.organization",
    "pk": 2,
    "fields": {
      "title": "org1",
      "short_name": "short",
      "organization_kind": null,
      "methodology": "meth",
      "source_detail_methodology": "ddd",
      "parent": null
    }
  }
]